cookies.py
test_cookies.py
cookies-2.1.0.dist-info/RECORD
cookies-2.1.0.dist-info/metadata.json
cookies-2.1.0.dist-info/WHEEL
cookies-2.1.0.dist-info/DESCRIPTION.rst
cookies-2.1.0.dist-info/METADATA
cookies-2.1.0.dist-info/top_level.txt
